dbt/adapters/iomete/__init__.py
dbt/adapters/iomete/__version__.py
dbt/adapters/iomete/column.py
dbt/adapters/iomete/connections.py
dbt/adapters/iomete/impl.py
dbt/adapters/iomete/python_job.py
dbt/adapters/iomete/relation.py
dbt/adapters/iomete/schema_service.py
dbt/include/iomete/__init__.py
dbt/include/iomete/dbt_project.yml
dbt/include/iomete/profile_template.yml
dbt/include/iomete/macros/adapters.sql
dbt/include/iomete/macros/materializations/seed.sql
dbt/include/iomete/macros/materializations/snapshot.sql
dbt/include/iomete/macros/materializations/table.sql
dbt/include/iomete/macros/materializations/view.sql
dbt/include/iomete/macros/materializations/incremental/incremental.sql
dbt/include/iomete/macros/materializations/incremental/strategies.sql
dbt/include/iomete/macros/materializations/incremental/validate.sql
dbt_iomete-1.7.3.dist-info/METADATA
dbt_iomete-1.7.3.dist-info/WHEEL
dbt_iomete-1.7.3.dist-info/top_level.txt
dbt_iomete-1.7.3.dist-info/RECORD
