Metadata-Version: 2.1
Name: dbt-iomete
Version: 1.7.3
Summary: The Apache Spark (IOMETE) adapter plugin for dbt
Home-page: https://github.com/iomete/dbt-iomete
Author: iomete
Author-email: support@iomete.com
Classifier: Development Status :: 5 - Production/Stable
Classifier: License :: OSI Approved :: Apache Software License
Classifier: Operating System :: Microsoft :: Windows
Classifier: Operating System :: MacOS :: MacOS X
Classifier: Operating System :: POSIX :: Linux
Classifier: Programming Language :: Python :: 3.7
Classifier: Programming Language :: Python :: 3.8
Classifier: Programming Language :: Python :: 3.9
Requires-Python: >=3.7
Requires-Dist: dbt-core ~=1.7.0
Requires-Dist: sqlparams >=3.0.0
Requires-Dist: py-hive-iomete >=2.1.0
Requires-Dist: sentry-sdk ==1.11.1
Requires-Dist: iomete-sdk ==2.0.0
